odoo/addons/account_usability/README.rst
odoo/addons/account_usability/__init__.py
odoo/addons/account_usability/__manifest__.py
odoo/addons/account_usability/data/ir_module_category.xml
odoo/addons/account_usability/demo/res_groups.xml
odoo/addons/account_usability/i18n/account_usability.pot
odoo/addons/account_usability/i18n/ar.po
odoo/addons/account_usability/i18n/es.po
odoo/addons/account_usability/i18n/fr.po
odoo/addons/account_usability/i18n/fr_FR.po
odoo/addons/account_usability/i18n/hr.po
odoo/addons/account_usability/i18n/it.po
odoo/addons/account_usability/i18n/nl.po
odoo/addons/account_usability/i18n/pt.po
odoo/addons/account_usability/i18n/pt_BR.po
odoo/addons/account_usability/i18n/tr.po
odoo/addons/account_usability/models/__init__.py
odoo/addons/account_usability/models/account_account.py
odoo/addons/account_usability/models/account_group.py
odoo/addons/account_usability/models/account_tag.py
odoo/addons/account_usability/models/account_tax_group.py
odoo/addons/account_usability/models/res_config_settings.py
odoo/addons/account_usability/readme/CONTRIBUTORS.md
odoo/addons/account_usability/readme/DESCRIPTION.md
odoo/addons/account_usability/readme/DEVELOP.md
odoo/addons/account_usability/readme/ROADMAP.md
odoo/addons/account_usability/security/res_groups.xml
odoo/addons/account_usability/static/description/icon.png
odoo/addons/account_usability/static/description/index.html
odoo/addons/account_usability/tests/__init__.py
odoo/addons/account_usability/tests/test_account_group.py
odoo/addons/account_usability/views/menu.xml
odoo/addons/account_usability/views/res_config_settings_views.xml
odoo/addons/account_usability/views/view_account_bank_statement.xml
odoo/addons/account_usability/views/view_account_group.xml
odoo/addons/account_usability/views/view_account_move_line.xml
odoo/addons/account_usability/views/view_account_tag.xml
odoo_addon_account_usability-19.0.1.0.0.2.dist-info/METADATA
odoo_addon_account_usability-19.0.1.0.0.2.dist-info/WHEEL
odoo_addon_account_usability-19.0.1.0.0.2.dist-info/top_level.txt
odoo_addon_account_usability-19.0.1.0.0.2.dist-info/RECORD
