Metadata-Version: 2.1
Name: odoo-addon-account_usability
Version: 19.0.1.0.0.2
Requires-Dist: odoo==19.0.*
Summary: Adds missing menu entries for Account module and adds the option to enable Saxon Accounting
Home-page: https://github.com/OCA/account-financial-tools
License: AGPL-3
Author: GRAP, Akretion, Odoo Community Association (OCA)
Author-email: support@odoo-community.org
Classifier: Programming Language :: Python
Classifier: Framework :: Odoo
Classifier: Framework :: Odoo :: 19.0
Classifier: License :: OSI Approved :: GNU Affero General Public License v3
